[
  {
    "BESTSELLER": true,
    "title": "Back in Black",
    "artist": "AC/DC",
    "rating": 10,
    "release_date": "1980-07-25",
    "genre": "Rock",
    "stock": 15,
    "precio": 89.99,
    "image": "album_images/back_in_black.jpg"
  },
  {
    "BESTSELLER": false,
    "title": "Is This It",
    "artist": "The Strokes",
    "rating": 9,
    "release_date": "2001-07-30",
    "genre": "Indie Rock",
    "stock": 10,
    "precio": 79.99,
    "image": "album_images/is_this_it.jpg"
  },
  {
    "BESTSELLER": false,
    "title": "Bloom",
    "artist": "Beach House",
    "rating": 8,
    "release_date": "2012-05-15",
    "genre": "Indie Pop",
    "stock": 8,
    "precio": 74.99,
    "image": "album_images/bloom.jpg"
  },
  {
    "BESTSELLER": false,
    "title": "OK Computer",
    "artist": "Radiohead",
    "rating": 10,
    "release_date": "1997-05-21",
    "genre": "Alternative Rock",
    "stock": 12,
    "precio": 89.99,
    "image": "album_images/ok_computer.jpg"
  },
  {
    "BESTSELLER": false,
    "title": "Master of Puppets",
    "artist": "Metallica",
    "rating": 10,
    "release_date": "1986-03-03",
    "genre": "Metal",
    "stock": 9,
    "precio": 99.99,
    "image": "album_images/master_of_puppets.jpg"
  },
  {
    "BESTSELLER": false,
    "title": "Dookie",
    "artist": "Green Day",
    "rating": 9,
    "release_date": "1994-02-01",
    "genre": "Punk",
    "stock": 7,
    "precio": 69.99,
    "image": "album_images/dookie.jpg"
  },
  {
    "BESTSELLER": true,
    "title": "Thriller",
    "artist": "Michael Jackson",
    "rating": 10,
    "release_date": "1982-11-30",
    "genre": "Pop",
    "stock": 20,
    "precio": 89.99,
    "image": "album_images/thriller.jpg"
  },
  {
    "BESTSELLER": false,
    "title": "Love Dive",
    "artist": "IVE",
    "rating": 8,
    "release_date": "2022-04-05",
    "genre": "K-pop",
    "stock": 13,
    "precio": 59.99,
    "image": "album_images/love_dive.jpg"
  },
  {
    "BESTSELLER": false,
    "title": "First Love",
    "artist": "Hikaru Utada",
    "rating": 9,
    "release_date": "1999-03-10",
    "genre": "J-pop",
    "stock": 5,
    "precio": 84.99,
    "image": "album_images/first_love.jpg"
  },
  {
    "BESTSELLER": false,
    "title": "Kind of Blue",
    "artist": "Miles Davis",
    "rating": 10,
    "release_date": "1959-08-17",
    "genre": "Jazz",
    "stock": 10,
    "precio": 94.99,
    "image": "album_images/kind_of_blue.jpg"
  },
  {
    "BESTSELLER": false,
    "title": "Born Under a Bad Sign",
    "artist": "Albert King",
    "rating": 8,
    "release_date": "1967-08-01",
    "genre": "Blues",
    "stock": 6,
    "precio": 69.99,
    "image": "album_images/born_under_a_bad_sign.jpg"
  },
  {
    "BESTSELLER": false,
    "title": "Discovery",
    "artist": "Daft Punk",
    "rating": 9,
    "release_date": "2001-03-13",
    "genre": "Disco",
    "stock": 11,
    "precio": 79.99,
    "image": "album_images/discovery.jpg"
  },
  {
    "BESTSELLER": false,
    "title": "El Malo",
    "artist": "Willie Colón",
    "rating": 8,
    "release_date": "1967-09-01",
    "genre": "Salsa",
    "stock": 15,
    "precio": 59.99,
    "image": "album_images/el_malo.jpg"
  },
  {
    "BESTSELLER": false,
    "title": "Bachata Rosa",
    "artist": "Juan Luis Guerra",
    "rating": 10,
    "release_date": "1990-08-20",
    "genre": "Bachata",
    "stock": 14,
    "precio": 74.99,
    "image": "album_images/bachata_rosa.jpg"
  },
  {
    "BESTSELLER": true,
    "title": "Barrio Fino",
    "artist": "Daddy Yankee",
    "rating": 10,
    "release_date": "2004-07-13",
    "genre": "Reggaeton",
    "stock": 25,
    "precio": 84.99,
    "image": "album_images/barrio_fino.jpg"
  },
  {
    "BESTSELLER": false,
    "title": "El Ritmo de la Noche",
    "artist": "The Sacados",
    "rating": 8,
    "release_date": "1990-10-15",
    "genre": "Cumbia",
    "stock": 10,
    "precio": 64.99,
    "image": "album_images/el_ritmo_de_la_noche.jpg"
  },
  {
    "BESTSELLER": false,
    "title": "Dembow Mundial",
    "artist": "El Alfa",
    "rating": 9,
    "release_date": "2021-10-01",
    "genre": "Dembow",
    "stock": 12,
    "precio": 79.99,
    "image": "album_images/dembow_mundial.jpg"
  },
  {
    "BESTSELLER": false,
    "title": "La Voz Romántica",
    "artist": "Lucho Gatica",
    "rating": 8,
    "release_date": "1958-05-10",
    "genre": "Bolero",
    "stock": 7,
    "precio": 59.99,
    "image": "album_images/la_voz_romantica.jpg"
  },
  {
    "BESTSELLER": false,
    "title": "Random Access Memories",
    "artist": "Daft Punk",
    "rating": 10,
    "release_date": "2013-05-17",
    "genre": "Electronic",
    "stock": 14,
    "precio": 89.99,
    "image": "album_images/ram.jpg"
  },
  {
    "BESTSELLER": false,
    "title": "Minimal Nation",
    "artist": "Robert Hood",
    "rating": 8,
    "release_date": "1994-05-01",
    "genre": "Techno",
    "stock": 6,
    "precio": 74.99,
    "image": "album_images/minimal_nation.jpg"
  },
  {
    "BESTSELLER": false,
    "title": "Illmatic",
    "artist": "Nas",
    "rating": 10,
    "release_date": "1994-04-19",
    "genre": "Hip Hop",
    "stock": 18,
    "precio": 79.99,
    "image": "album_images/illmatic.jpg"
  },
  {
    "BESTSELLER": false,
    "title": "Legend",
    "artist": "Bob Marley & The Wailers",
    "rating": 10,
    "release_date": "1984-05-08",
    "genre": "Reggae",
    "stock": 20,
    "precio": 79.99,
    "image": "album_images/legend.jpg"
  },
  {
    "BESTSELLER": false,
    "title": "El Madrileño",
    "artist": "C. Tangana",
    "rating": 8,
    "release_date": "2021-02-26",
    "genre": "Trap",
    "stock": 16,
    "precio": 69.99,
    "image": "album_images/el_madrileno.jpg"
  }
]
